{
  "event_data":{
    "name":"event_data",
    "title":"Event data",
    "extends":"Event",
    "style":"Inline",
    "is_active":1,
    "is_reserved":0,
    "collapse_display":0,
    "table_name":"custom_event_data",
    "fields": {
      "nt_org": {
        "name": "nt_org",
        "label": "National Organization",
        "option_group": "nt_org",
        "data_type": "String",
        "html_type": "Select",
        "is_searchable": 1,
        "is_view": 0,
        "column_name": "nt_org",
        "weight": -40,
        "is_active": 1
      },
      "area": {
        "name": "area",
        "label": "Area",
        "option_group": "area",
        "data_type": "String",
        "html_type": "Select",
        "is_searchable": 1,
        "is_view": 0,
        "column_name": "area",
        "weight": -40,
        "is_active": 1
      },
      "mnry": {
        "name": "mnry",
        "label": "Ministry",
        "option_group": "mnry",
        "data_type": "String",
        "html_type": "Multi-Select",
        "is_searchable": 1,
        "is_view": 0,
        "column_name": "mnry",
        "weight": -40,
        "is_active": 1
      },
      "chlg": {
        "name": "chlg",
        "label": "Challenge",
        "option_group": "dsc_pathway",
        "data_type": "String",
        "html_type": "CheckBox",
        "is_searchable": 1,
        "is_view": 0,
        "column_name": "chlg",
        "weight": -40,
        "is_active": 1
      },
      "hway": {
        "name": "hway",
        "label": "Highway",
        "option_group": "hway",
        "data_type": "String",
        "html_type": "CheckBox",
        "is_searchable": 1,
        "is_view": 0,
        "column_name": "hway",
        "weight": -40,
        "is_active": 1
      },
      "spons": {
        "name": "spons",
        "label": "Sponsored by",
        "option_group": "spons",
        "data_type": "String",
        "html_type": "CheckBox",
        "is_searchable": 1,
        "is_view": 0,
        "column_name": "spons",
        "weight": -40,
        "is_active": 1
      },
      "src": {
        "name": "src",
        "label": "Source",
        "option_group": "src",
        "data_type": "String",
        "html_type": "Select",
        "is_searchable": 1,
        "is_view": 0,
        "column_name": "src_cd",
        "weight": -40,
        "is_active": 1
      },
      "src_sys": {
        "name": "src_sys",
        "label": "Source system",
        "option_group": "src_sys",
        "data_type": "String",
        "html_type": "Select",
        "is_searchable": 1,
        "is_view": 0,
        "column_name": "src_sys_id",
        "weight": -40,
        "is_active": 1
      }
    }
  },
  "event_metrics":{
    "name":"event_metrics",
    "title":"Event metrics",
    "extends":"Event",
    "style":"Inline",
    "is_active":1,
    "is_reserved":0,
    "collapse_display":0,
    "table_name":"custom_event_metrics",
    "fields": {
      "attn": {
        "name": "attn",
        "label": "Attendance",
        "data_type": "Integer",
        "html_type": "Text",
        "is_searchable": 1,
        "is_view": 0,
        "column_name": "attn_cnt",
        "weight": -40,
        "is_active": 1
      },
      "blv": {
        "name": "blv",
        "label": "Believers",
        "data_type": "Integer",
        "html_type": "Text",
        "is_searchable": 1,
        "is_view": 0,
        "column_name": "blv_cnt",
        "weight": -40,
        "is_active": 1
      },
      "unb": {
        "name": "unb",
        "label": "Unbelievers",
        "data_type": "Integer",
        "html_type": "Text",
        "is_searchable": 1,
        "is_view": 0,
        "column_name": "unb_cnt",
        "weight": -40,
        "is_active": 1
      },
      "fyg": {
        "name": "fyg",
        "label": "Foreign youth group attendees",
        "data_type": "Integer",
        "html_type": "Text",
        "is_searchable": 1,
        "is_view": 0,
        "column_name": "fyg_cnt",
        "weight": -40,
        "is_active": 1
      },
      "pof": {
        "name": "pof",
        "label": "Professions of faith",
        "data_type": "Integer",
        "html_type": "Text",
        "is_searchable": 1,
        "is_view": 0,
        "column_name": "pof_cnt",
        "weight": -40,
        "is_active": 1
      },
      "rof": {
        "name": "rof",
        "label": "Reaffirmations of faith",
        "data_type": "Integer",
        "html_type": "Text",
        "is_searchable": 1,
        "is_view": 0,
        "column_name": "rof_cnt",
        "weight": -40,
        "is_active": 1
      }
    }
  },
  "ind_data":{
    "name":"ind_data",
    "title":"Individual data",
    "extends":"Individual",
    "style":"Inline",
    "is_active":1,
    "is_reserved":0,
    "collapse_display":0,
    "table_name":"custom_ind_data",
    "fields": {
      "dsc_pathway": {
        "name": "dsc_pathway",
        "label": "Discipleship pathway",
        "option_group": "dsc_pathway",
        "data_type": "String",
        "html_type": "Radio",
        "is_searchable": 1,
        "is_view": 0,
        "column_name": "dsc_pathway",
        "weight": -40,
        "is_active": 1
      },
      "ldr_pathway": {
        "name": "ldr_pathway",
        "label": "Leadership pathway",
        "option_group": "ldr_pathway",
        "data_type": "String",
        "html_type": "Radio",
        "is_searchable": 1,
        "is_view": 0,
        "column_name": "ldr_pathway",
        "weight": -40,
        "is_active": 1
      },
      "natl": {
        "name": "natl",
        "label": "Nationality",
        "option_group": "natl",
        "data_type": "String",
        "html_type": "Select",
        "is_searchable": 1,
        "is_view": 0,
        "column_name": "natl",
        "weight": -40,
        "is_active": 1
      }
    }
  },
  "org_ch_data":{
  "name":"church_data",
  "title":"Church data",
  "extends":"Organization",
  "extends_entity_column_value":"church",
  "style":"Inline",
  "is_active":1,
  "is_reserved":0,
  "collapse_display":0,
  "table_name":"custom_church_data",
  "fields": {
    "dsc_pathway": {
      "name": "mnry_phase",
      "label": "Ministry phase",
      "option_group": "mnry_phase",
      "data_type": "String",
      "html_type": "Radio",
      "is_searchable": 1,
      "is_view": 0,
      "column_name": "mnry_phase",
      "weight": -40,
      "is_active": 1
    }
  }
  },
  "ch_gr_data":{
    "name":"chgrp_data",
    "title":"Church group data",
    "extends":"Organization",
    "extends_entity_column_value":"church_group",
    "style":"Inline",
    "is_active":1,
    "is_reserved":0,
    "collapse_display":0,
    "table_name":"custom_chgrp_data",
    "fields": {
      "dsc_pathway": {
        "name": "mnry_phase",
        "label": "Ministry phase",
        "option_group": "mnry_phase",
        "data_type": "String",
        "html_type": "Radio",
        "is_searchable": 1,
        "is_view": 0,
        "column_name": "mnry_phase",
        "weight": -40,
        "is_active": 1
      }
    }
  },
  "band_data":{
    "name":"band_data",
    "title":"Band data",
    "extends":"Organization",
    "extends_entity_column_value":"band",
    "style":"Inline",
    "is_active":1,
    "is_reserved":0,
    "collapse_display":0,
    "table_name":"custom_band_data",
    "fields": {
      "mnry": {
        "name": "mnry",
        "label": "Band ministry",
        "option_group": "mnry",
        "data_type": "String",
        "html_type": "Multi-Select",
        "is_searchable": 1,
        "is_view": 0,
        "column_name": "mnry",
        "weight": -40,
        "is_active": 1
      }
    }
  },
  "band_avl":{
    "name":"band_avl",
    "title":"Band availability",
    "extends":"Organization",
    "extends_entity_column_value":"band",
    "style":"Tab with table",
    "is_active":1,
    "is_reserved":0,
    "collapse_display":0,
    "table_name":"custom_band_avl",
    "fields": {
      "from_dt": {
        "name": "from_dt",
        "label": "From date",
        "data_type": "Date",
        "html_type": "Select Date",
        "is_searchable": 1,
        "is_view": 0,
        "column_name": "from_dt",
        "weight": -40,
        "is_active": 1
      },
      "till_dt": {
        "name": "till_dt",
        "label": "Till date",
        "data_type": "Date",
        "html_type": "Select Date",
        "is_searchable": 1,
        "is_view": 0,
        "column_name": "till_dt",
        "weight": -40,
        "is_active": 1
      }
    }
  },
  "materials":{
    "name":"materials",
    "title":"Materials",
    "extends":"Organization",
    "extends_entity_column_value":"",
    "style":"Tab with table",
    "is_active":1,
    "is_reserved":0,
    "collapse_display":0,
    "table_name":"custom_materials",
    "fields": {
      "received_dt": {
        "name": "received_dt",
        "label": "Received date",
        "data_type": "Date",
        "html_type": "Select Date",
        "is_searchable": 1,
        "is_view": 0,
        "column_name": "received_dt",
        "weight": -40,
        "is_active": 1
      },
      "material": {
        "name": "material",
        "label": "Material",
        "option_group": "material",
        "data_type": "String",
        "html_type": "Multi-Select",
        "is_searchable": 1,
        "is_view": 0,
        "column_name": "material",
        "weight": -40,
        "is_active": 1
      },
      "quantity": {
        "name": "quantity",
        "label": "Quantity",
        "data_type": "Integer",
        "html_type": "Text",
        "is_searchable": 1,
        "is_view": 0,
        "column_name": "quantity",
        "weight": -40,
        "is_active": 1
      },
      "receiver": {
        "name": "receiver",
        "label": "Receiver",
        "data_type": "ContactReference",
        "html_type": "Autocomplete-Select",
        "is_searchable": 1,
        "is_view": 0,
        "column_name": "receiver",
        "weight": -40,
        "is_active": 1
      },
      "staff": {
        "name": "staff",
        "label": "Handed over by",
        "data_type": "ContactReference",
        "html_type": "Autocomplete-Select",
        "is_searchable": 1,
        "is_view": 0,
        "column_name": "staff",
        "weight": -40,
        "is_active": 1
      }
    }
  },
  "activity_data":{
    "name":"activity_data",
    "title":"Activity data",
    "extends":"Activity",
    "extends_entity_column_value":"",
    "style":"Inline",
    "is_active":1,
    "is_reserved":0,
    "collapse_display":0,
    "table_name":"custom_activity_data",
    "fields": {
      "nt_org": {
        "name": "nt_org",
        "label": "National Organization",
        "option_group": "nt_org",
        "data_type": "String",
        "html_type": "Select",
        "is_searchable": 1,
        "is_view": 0,
        "column_name": "nt_org",
        "weight": -40,
        "is_active": 1
      },
      "act_purp_1": {
        "name": "act_purp_1",
        "label": "Purpose 1",
        "option_group": "act_purp_1",
        "data_type":"String",
        "html_type":"Radio",
        "is_searchable":1,
        "is_view":0,
        "column_name":"act_purp_1",
        "weight":-130,
        "is_active":1
      },
      "act_purp_2": {
        "name": "act_purp_2",
        "label": "Purpose 2",
        "option_group": "act_purp_2",
        "data_type":"String",
        "html_type":"Radio",
        "is_searchable":1,
        "is_view":0,
        "column_name":"act_purp_2",
        "weight":-130,
        "is_active":1
      },
      "private": {
        "name": "is_private",
        "label": "Private",
        "data_type":"Boolean",
        "html_type":"Radio",
        "is_searchable":1,
        "is_view":0,
        "column_name":"is_private",
        "weight":-130,
        "is_active":1
      },
      "src": {
        "name": "src",
        "label": "Source",
        "option_group": "src",
        "data_type": "String",
        "html_type": "Select",
        "is_searchable": 1,
        "is_view": 0,
        "column_name": "src_cd",
        "weight": -40,
        "is_active": 1
      },
      "src_sys": {
        "name": "src_sys",
        "label": "Source system",
        "option_group": "src_sys",
        "data_type": "String",
        "html_type": "Select",
        "is_searchable": 1,
        "is_view": 0,
        "column_name": "src_sys_id",
        "weight": -40,
        "is_active": 1
      }
    }
  },
  "act_eval_data":{
     "name":"act_eval_data",
     "title":"Evaluation data",
     "extends":"Activity",
     "extends_entity_column_value":"evaluation",
     "style":"Inline",
     "is_active":1,
     "is_reserved":0,
     "collapse_display":0,
     "table_name":"custom_act_eval_data",
     "fields": {
     "blv": {
        "name": "blv",
        "label": "AVG believers",
        "data_type": "Integer",
        "html_type": "Text",
        "is_searchable": 1,
        "is_view": 0,
        "column_name": "blv_cnt",
        "weight": -40,
        "is_active": 1
      },
      "unb": {
        "name": "unb",
        "label": "AVG unbelievers",
        "data_type": "Integer",
        "html_type": "Text",
        "is_searchable": 1,
        "is_view": 0,
        "column_name": "unb_cnt",
        "weight": -40,
        "is_active": 1
      },
       "conv": {
         "name": "conv",
         "label": "Conversions",
         "data_type": "Integer",
         "html_type": "Text",
         "is_searchable": 1,
         "is_view": 0,
         "column_name": "conv_cnt",
         "weight": -40,
         "is_active": 1
       },
       "bapt": {
         "name": "bapt",
         "label": "Baptisms",
         "data_type": "Integer",
         "html_type": "Text",
         "is_searchable": 1,
         "is_view": 0,
         "column_name": "bapt_cnt",
         "weight": -40,
         "is_active": 1
       }
    }
  }
}
